odclib/__init__.py
odclib/bin/odc
odclib/include/odc/Block.h
odclib/include/odc/CommandLineParser.h
odclib/include/odc/Comparator.h
odclib/include/odc/ConstantSetter.cc
odclib/include/odc/ConstantSetter.h
odclib/include/odc/DispatchingWriter.h
odclib/include/odc/Indexer.h
odclib/include/odc/IteratorProxy.h
odclib/include/odc/LibOdc.h
odclib/include/odc/MDI.h
odclib/include/odc/MDSetter.h
odclib/include/odc/MDUpdatingIterator.cc
odclib/include/odc/MDUpdatingIterator.h
odclib/include/odc/ODAHandle.h
odclib/include/odc/ODATranslator.h
odclib/include/odc/ODAUpdatingIterator.cc
odclib/include/odc/ODAUpdatingIterator.h
odclib/include/odc/ODBAPISettings.h
odclib/include/odc/ODBAPIVersion.h
odclib/include/odc/ODBApplication.h
odclib/include/odc/ODBTarget.h
odclib/include/odc/Reader.h
odclib/include/odc/ReaderIterator.h
odclib/include/odc/RequestUtils.h
odclib/include/odc/RowsCounter.h
odclib/include/odc/Select.h
odclib/include/odc/SelectIterator.h
odclib/include/odc/StringTool.h
odclib/include/odc/TemplateParameters.h
odclib/include/odc/Writer.h
odclib/include/odc/WriterBufferingIterator.h
odclib/include/odc/WriterDispatchingIterator.cc
odclib/include/odc/WriterDispatchingIterator.h
odclib/include/odc/odc_config.h
odclib/include/odc/odc_ecbuild_config.h
odclib/include/odc/odccapi.h
odclib/include/odc/pyodbapi.h
odclib/include/odc/api/ColumnInfo.h
odclib/include/odc/api/ColumnType.h
odclib/include/odc/api/Odb.h
odclib/include/odc/api/StridedData.h
odclib/include/odc/api/odc.h
odclib/include/odc/codec/CodecOptimizer.h
odclib/include/odc/codec/Constant.h
odclib/include/odc/codec/Integer.h
odclib/include/odc/codec/IntegerMissing.h
odclib/include/odc/codec/Real.h
odclib/include/odc/codec/String.h
odclib/include/odc/core/Codec.h
odclib/include/odc/core/CodecFactory.h
odclib/include/odc/core/Column.h
odclib/include/odc/core/DataStream.h
odclib/include/odc/core/DecodeTarget.h
odclib/include/odc/core/Encoder.h
odclib/include/odc/core/Exceptions.h
odclib/include/odc/core/Header.h
odclib-1.6.2.9.dist-info/licenses/LICENSE
odclib-1.6.2.9.dist-info/METADATA
odclib-1.6.2.9.dist-info/WHEEL
odclib-1.6.2.9.dist-info/top_level.txt
odclib-1.6.2.9.dist-info/RECORD
