Metadata-Version: 2.4
Name: odclib
Version: 1.6.2.9
Summary: "odclib"
Author: file: AUTHORS
License-File: LICENSE
Requires-Dist: eckitlib==1.32.4.9
Dynamic: license-file
Dynamic: requires-dist
